<?xml version="1.0" encoding="utf-8"?>
<TextureAtlas imagePath="steklobaba.png">
	<!-- Created with Adobe Animate version 22.0.1.105 -->
	<!-- http://www.adobe.com/products/animate.html -->
	<SubTexture name="SB-down0000" x="5" y="5" width="477" height="863"/>
	<SubTexture name="SB-down0001" x="5" y="5" width="477" height="863"/>
	<SubTexture name="SB-down0002" x="487" y="5" width="477" height="863"/>
	<SubTexture name="SB-down0003" x="487" y="5" width="477" height="863"/>
	<SubTexture name="SB-down0004" x="969" y="5" width="477" height="863"/>
	<SubTexture name="SB-down0005" x="969" y="5" width="477" height="863"/>
	<SubTexture name="SB-down0006" x="969" y="5" width="477" height="863"/>
	<SubTexture name="SB-down0007" x="969" y="5" width="477" height="863"/>
	<SubTexture name="SB-down0008" x="969" y="5" width="477" height="863"/>
	<SubTexture name="SB-down0009" x="969" y="5" width="477" height="863"/>
	<SubTexture name="SB-idle0000" x="1451" y="5" width="379" height="919"/>
	<SubTexture name="SB-idle0001" x="1451" y="5" width="379" height="919"/>
	<SubTexture name="SB-idle0002" x="1835" y="5" width="379" height="919"/>
	<SubTexture name="SB-idle0003" x="1835" y="5" width="379" height="919"/>
	<SubTexture name="SB-idle0004" x="2219" y="5" width="379" height="919"/>
	<SubTexture name="SB-idle0005" x="2219" y="5" width="379" height="919"/>
	<SubTexture name="SB-idle0006" x="2603" y="5" width="379" height="919"/>
	<SubTexture name="SB-idle0007" x="2603" y="5" width="379" height="919"/>
	<SubTexture name="SB-idle0008" x="2987" y="5" width="379" height="919"/>
	<SubTexture name="SB-idle0009" x="2987" y="5" width="379" height="919"/>
	<SubTexture name="SB-idle0010" x="3371" y="5" width="379" height="919"/>
	<SubTexture name="SB-idle0011" x="3371" y="5" width="379" height="919"/>
	<SubTexture name="SB-idle0012" x="3371" y="5" width="379" height="919"/>
	<SubTexture name="SB-idle0013" x="3371" y="5" width="379" height="919"/>
	<SubTexture name="SB-idle0014" x="3371" y="5" width="379" height="919"/>
	<SubTexture name="SB-left0000" x="3755" y="5" width="734" height="918"/>
	<SubTexture name="SB-left0001" x="3755" y="5" width="734" height="918"/>
	<SubTexture name="SB-left0002" x="4494" y="5" width="734" height="918"/>
	<SubTexture name="SB-left0003" x="4494" y="5" width="734" height="918"/>
	<SubTexture name="SB-left0004" x="5233" y="5" width="734" height="918"/>
	<SubTexture name="SB-left0005" x="5233" y="5" width="734" height="918"/>
	<SubTexture name="SB-left0006" x="5233" y="5" width="734" height="918"/>
	<SubTexture name="SB-left0007" x="5233" y="5" width="734" height="918"/>
	<SubTexture name="SB-left0008" x="5233" y="5" width="734" height="918"/>
	<SubTexture name="SB-left0009" x="5233" y="5" width="734" height="918"/>
	<SubTexture name="SB-reload0000" x="5972" y="5" width="412" height="919"/>
	<SubTexture name="SB-reload0001" x="6389" y="5" width="412" height="919"/>
	<SubTexture name="SB-reload0002" x="6806" y="5" width="412" height="919"/>
	<SubTexture name="SB-reload0003" x="7223" y="5" width="412" height="919"/>
	<SubTexture name="SB-reload0004" x="7223" y="5" width="412" height="919"/>
	<SubTexture name="SB-reload0005" x="7640" y="5" width="412" height="919"/>
	<SubTexture name="SB-reload0006" x="7640" y="5" width="412" height="919"/>
	<SubTexture name="SB-reload0007" x="7640" y="5" width="412" height="919"/>
	<SubTexture name="SB-reload0008" x="5" y="929" width="412" height="919"/>
	<SubTexture name="SB-reload0009" x="5" y="929" width="412" height="919"/>
	<SubTexture name="SB-reload0010" x="422" y="929" width="412" height="919"/>
	<SubTexture name="SB-reload0011" x="422" y="929" width="412" height="919"/>
	<SubTexture name="SB-reload0012" x="839" y="929" width="412" height="919"/>
	<SubTexture name="SB-reload0013" x="839" y="929" width="412" height="919"/>
	<SubTexture name="SB-reload0014" x="839" y="929" width="412" height="919"/>
	<SubTexture name="SB-reload0015" x="1256" y="929" width="412" height="919"/>
	<SubTexture name="SB-reload0016" x="1673" y="929" width="412" height="919"/>
	<SubTexture name="SB-reload0017" x="1673" y="929" width="412" height="919"/>
	<SubTexture name="SB-reload0018" x="2090" y="929" width="412" height="919"/>
	<SubTexture name="SB-reload0019" x="2090" y="929" width="412" height="919"/>
	<SubTexture name="SB-reload0020" x="2507" y="929" width="412" height="919"/>
	<SubTexture name="SB-reload0021" x="2507" y="929" width="412" height="919"/>
	<SubTexture name="SB-reload0022" x="2924" y="929" width="412" height="919"/>
	<SubTexture name="SB-reload0023" x="2924" y="929" width="412" height="919"/>
	<SubTexture name="SB-reload0024" x="3341" y="929" width="412" height="919"/>
	<SubTexture name="SB-reload0025" x="3758" y="929" width="412" height="919"/>
	<SubTexture name="SB-reload0026" x="3758" y="929" width="412" height="919"/>
	<SubTexture name="SB-reload0027" x="4175" y="929" width="412" height="919"/>
	<SubTexture name="SB-reload0028" x="4175" y="929" width="412" height="919"/>
	<SubTexture name="SB-reload0029" x="5972" y="5" width="412" height="919"/>
	<SubTexture name="SB-right0000" x="4592" y="929" width="513" height="923"/>
	<SubTexture name="SB-right0001" x="4592" y="929" width="513" height="923"/>
	<SubTexture name="SB-right0002" x="5110" y="929" width="513" height="923"/>
	<SubTexture name="SB-right0003" x="5110" y="929" width="513" height="923"/>
	<SubTexture name="SB-right0004" x="5628" y="929" width="513" height="923"/>
	<SubTexture name="SB-right0005" x="5628" y="929" width="513" height="923"/>
	<SubTexture name="SB-right0006" x="5628" y="929" width="513" height="923"/>
	<SubTexture name="SB-right0007" x="5628" y="929" width="513" height="923"/>
	<SubTexture name="SB-right0008" x="5628" y="929" width="513" height="923"/>
	<SubTexture name="SB-right0009" x="5628" y="929" width="513" height="923"/>
	<SubTexture name="SB-shoot0000" x="6146" y="929" width="493" height="924"/>
	<SubTexture name="SB-shoot0001" x="6644" y="929" width="493" height="924"/>
	<SubTexture name="SB-shoot0002" x="7142" y="929" width="493" height="924"/>
	<SubTexture name="SB-shoot0003" x="7640" y="929" width="493" height="924"/>
	<SubTexture name="SB-shoot0004" x="5" y="1858" width="493" height="924"/>
	<SubTexture name="SB-shoot0005" x="5" y="1858" width="493" height="924"/>
	<SubTexture name="SB-shoot0006" x="503" y="1858" width="493" height="924"/>
	<SubTexture name="SB-shoot0007" x="503" y="1858" width="493" height="924"/>
	<SubTexture name="SB-shoot0008" x="1001" y="1858" width="493" height="924"/>
	<SubTexture name="SB-shoot0009" x="1499" y="1858" width="493" height="924"/>
	<SubTexture name="SB-up0000" x="1997" y="1858" width="639" height="956"/>
	<SubTexture name="SB-up0001" x="1997" y="1858" width="639" height="956"/>
	<SubTexture name="SB-up0002" x="2641" y="1858" width="639" height="956"/>
	<SubTexture name="SB-up0003" x="2641" y="1858" width="639" height="956"/>
	<SubTexture name="SB-up0004" x="3285" y="1858" width="639" height="956"/>
	<SubTexture name="SB-up0005" x="3285" y="1858" width="639" height="956"/>
	<SubTexture name="SB-up0006" x="3285" y="1858" width="639" height="956"/>
	<SubTexture name="SB-up0007" x="3285" y="1858" width="639" height="956"/>
	<SubTexture name="SB-up0008" x="3285" y="1858" width="639" height="956"/>
	<SubTexture name="SB-up0009" x="3285" y="1858" width="639" height="956"/>
</TextureAtlas>
